[
    {
        "index": "dragonborn",
        "name": "Draconato",
        "speed": 9,
        "ability_bonuses": [
            {
                "ability_score": {
                    "index": "str",
                    "name": "FOR",
                    "url": "/api/ability-scores/str"
                },
                "bonus": 2
            },
            {
                "ability_score": {
                    "index": "cha",
                    "name": "CAR",
                    "url": "/api/ability-scores/cha"
                },
                "bonus": 1
            }
        ],
        "alignment": "Os draconatos tendem aos extremos, realizando uma escolha consciente de um lado ou do outro da guerra cósmica entre o bem e o mal (representada por Bahamut e Tiamat, respectivamente). A maioria dos draconatos é boa, mas os que vão para o lado de Tiamat podem se tornar vilões terríveis.",
        "age": "Draconatos jovens crescem rapidamente. Eles caminham horas após nascerem, adquirindo o tamanho e desenvolvimento semelhante a de uma criança humana de 10 anos com 3 anos de idade e alcançam a maturidade aos 15. Eles costumam viver até os 80.",
        "size": "Médio",
        "size_description": "Os draconatos são mais altos e mais pesados que os humanos, geralmente possuindo mais de 1,80 metro e normalmente pesando mais de 125 kg",
        "starting_proficiencies": [],
        "languages": [
            {
                "index": "common",
                "name": "Comum",
                "url": "/api/languages/common"
            },
            {
                "index": "draconic",
                "name": "Dracônico",
                "url": "/api/languages/draconic"
            }
        ],
        "language_desc": " Você pode falar, ler e escrever Comum e Dracônico .O idioma Dracônico é conhecido por ser uma das mais antigas línguas e ainda é usado no estudo de magia. A linguagem soa áspera para a maioria das criaturas, incluindo várias consoantes e silabas firmes.",
        "traits": [
            {
                "index": "draconic-ancestry",
                "name": "Ancestral Dracônico",
                "url": "/api/traits/draconic-ancestry"
            },
            {
                "index": "breath-weapon",
                "name": "Arma de Sopro",
                "url": "/api/traits/breath-weapon"
            },
            {
                "index": "damage-resistance",
                "name": "Resistência a Dano",
                "url": "/api/traits/damage-resistance"
            }
        ],
        "subraces": [],
        "url": "/api/races/dragonborn"
    },
    {
        "index": "dwarf",
        "name": "Anão",
        "speed": 7.5,
        "ability_bonuses": [
            {
                "ability_score": {
                    "index": "con",
                    "name": "CON",
                    "url": "/api/ability-scores/con"
                },
                "bonus": 2
            }
        ],
        "alignment": "A maioria dos anões é leal, pois acreditam firmemente nos benefícios de uma sociedade bem organizada. Eles tendem para o bem, com um forte senso de honestidade e uma crença de que todos merecem compartilhar os benefícios de uma ordem social justa.",
        "age": "Anões tornam-se maduros na mesma proporção que os humanos, mas são considerados jovens até atingirem a idade de 50 anos. Em média, eles vivem 350 anos.",
        "size": "Médio",
        "size_description": "Anões estão entre 1,20 e 1,50 metro de altura e pesam cerca de 75 kg.",
        "starting_proficiencies": [
            {
                "index": "battleaxes",
                "name": "Machados de Batalha",
                "url": "/api/proficiencies/battleaxes"
            },
            {
                "index": "handaxes",
                "name": "Machadinhas",
                "url": "/api/proficiencies/handaxes"
            },
            {
                "index": "light-hammers",
                "name": "Martelos Leves",
                "url": "/api/proficiencies/light-hammers"
            },
            {
                "index": "warhammers",
                "name": "Martelos de Guerra",
                "url": "/api/proficiencies/warhammers"
            }
        ],
        "starting_proficiency_options": {
            "desc": "Você tem proficiência em uma ferramenta de artesão à sua escolha entre: ferramentas de ferreiro, suprimentos de cervejeiro ou ferramentas de pedreiro.",
            "choose": 1,
            "type": "proficiencies",
            "from": {
                "option_set_type": "options_array",
                "options": [
                    {
                        "option_type": "reference",
                        "item": {
                            "index": "smiths-tools",
                            "name": "Ferramentas de Ferreiro",
                            "url": "/api/proficiencies/smiths-tools"
                        }
                    },
                    {
                        "option_type": "reference",
                        "item": {
                            "index": "brewers-supplies",
                            "name": "Suprimentos de Cervejeiro",
                            "url": "/api/proficiencies/brewers-supplies"
                        }
                    },
                    {
                        "option_type": "reference",
                        "item": {
                            "index": "masons-tools",
                            "name": "Ferramentas de Pedreiro",
                            "url": "/api/proficiencies/masons-tools"
                        }
                    }
                ]
            }
        },
        "languages": [
            {
                "index": "common",
                "name": "Comum",
                "url": "/api/languages/common"
            },
            {
                "index": "dwarvish",
                "name": "Anão",
                "url": "/api/languages/dwarvish"
            }
        ],
        "language_desc": "Você pode falar, ler e escrever Comum e Anão. O idioma Anão é repleto de consoantes duras e sons guturais, e essa característica influencia, como um sotaque, qualquer outro idioma que o anão falar.",
        "traits": [
            {
                "index": "darkvision",
                "name": "Visão no Escuro",
                "url": "/api/traits/darkvision"
            },
            {
                "index": "dwarven-resilience",
                "name": "Resiliência Anã",
                "url": "/api/traits/dwarven-resilience"
            },
            {
                "index": "stonecunning",
                "name": "Especialização em Rochas",
                "url": "/api/traits/stonecunning"
            },
            {
                "index": "dwarven-combat-training",
                "name": "Treinamento Anão em Combate",
                "url": "/api/traits/dwarven-combat-training"
            },
            {
                "index": "tool-proficiency",
                "name": "Proficiência com Ferramentas",
                "url": "/api/traits/tool-proficiency"
            }
        ],
        "subraces": [
            {
                "index": "hill-dwarf",
                "name": "Anão da Colina",
                "url": "/api/subraces/hill-dwarf"
            }
        ],
        "url": "/api/races/dwarf"
    },
    {
        "index": "elf",
        "name": "Elfo",
        "speed": 9,
        "ability_bonuses": [
            {
                "ability_score": {
                    "index": "dex",
                    "name": "DES",
                    "url": "/api/ability-scores/dex"
                },
                "bonus": 2
            }
        ],
        "age": "Embora os elfos atinjam a maturidade física com praticamente a mesma idade dos humanos, a compreensão élfica da idade adulta vai além da maturidade física, abrangendo sua experiência sobre o mundo. Um elfo tipicamente assume a idade adulta e um nome adulto com cerca de 100 anos de idade e pode viver 750 anos.",
        "alignment": "Elfos amam a liberdade, a diversidade e a expressão pessoal, então eles inclinam-se forte e suavemente para aspectos do caos. Eles valorizam e protegem a liberdade dos outros como a sua própria, e são geralmente mais bondosos que o contrário. Os drow são exceção. Seu exílio no Subterrâneo fez deles perversos e perigosos. Drow são geralmente mais maus que o contrário.",
        "size": "Médio",
        "size_description": "Elfos medem entre 1,50 a 1,80 metro de altura e possuem constituição delgada.",
        "starting_proficiencies": [
            {
                "index": "skill-perception",
                "name": "Habilidade: Percepção",
                "url": "/api/proficiencies/skill-perception"
            }
        ],
        "languages": [
            {
                "index": "common",
                "name": "Comum",
                "url": "/api/languages/common"
            },
            {
                "index": "elvish",
                "name": "Elfico",
                "url": "/api/languages/elvish"
            }
        ],
        "language_desc": "Você pode falar, ler e escrever Comum e Élfico. O Élfico é um idioma fluido, com entonações sutis e gramática complexa. A literatura élfica é rica e diversa, e suas canções e poemas são famosos entre outras raças.",
        "traits": [
            {
                "index": "darkvision",
                "name": "Visão no Escuro",
                "url": "/api/traits/darkvision"
            },
            {
                "index": "fey-ancestry",
                "name": "Ancestral Feérico",
                "url": "/api/traits/fey-ancestry"
            },
            {
                "index": "trance",
                "name": "Transe",
                "url": "/api/traits/trance"
            },
            {
                "index": "keen-senses",
                "name": "Sentidos Aguçados",
                "url": "/api/traits/keen-senses"
            }
        ],
        "subraces": [
            {
                "index": "high-elf",
                "name": "Alto Elfo",
                "url": "/api/subraces/high-elf"
            }
        ],
        "url": "/api/races/elf"
    },
    {
        "index": "gnome",
        "name": "Gnomo",
        "speed": 7.5,
        "ability_bonuses": [
            {
                "ability_score": {
                    "index": "int",
                    "name": "INT",
                    "url": "/api/ability-scores/int"
                },
                "bonus": 2
            }
        ],
        "alignment": "Os gnomos geralmente são bons. Os que tendem para a ordem são sábios, engenheiros, pesquisadores, escolásticos, investigadores ou inventores. Os que tendem ao caos são menestréis, engenhoqueiros, andarilhos ou joalheiros caprichosos. Gnomos são bons de coração e, até mesmo os trapaceiros entre eles tendem a ser mais brincalhões que perversos.",
        "age": "Gnomos amadurecem a mesma proporção que os humanos e, a maioria, atinge a idade adulta por volta dos 40 anos. Eles podem viver entre 350 e 500 anos.",
        "size": "Pequeno",
        "size_description": "Os gnomos tem entre 0,90 e 1,20 metro e seu peso médio é de 20 kg.",
        "starting_proficiencies": [],
        "languages": [
            {
                "index": "common",
                "name": "Comum",
                "url": "/api/languages/common"
            },
            {
                "index": "gnomish",
                "name": "Gnômico",
                "url": "/api/languages/gnomish"
            }
        ],
        "language_desc": "Você sabe falar, ler e escrever Comum e Gnômico. A linguagem Gnômica, que usa o alfabeto Anão, é conhecida por suas técnicas de dissertação e por seus catálogos de conhecimento sobre o mundo natural.",
        "traits": [
            {
                "index": "darkvision",
                "name": "Visão no Escuro",
                "url": "/api/traits/darkvision"
            },
            {
                "index": "gnome-cunning",
                "name": "Esperteza Gnômica",
                "url": "/api/traits/gnome-cunning"
            }
        ],
        "subraces": [
            {
                "index": "rock-gnome",
                "name": "Gnomo das Rochas",
                "url": "/api/subraces/rock-gnome"
            }
        ],
        "url": "/api/races/gnome"
    },
    {
        "index": "half-elf",
        "name": "Meio-Elfo",
        "speed": 9,
        "ability_bonuses": [
            {
                "ability_score": {
                    "index": "cha",
                    "name": "CAR",
                    "url": "/api/ability-scores/cha"
                },
                "bonus": 2
            }
        ],
        "ability_bonus_options": {
            "choose": 2,
            "type": "ability_bonuses",
            "from": {
                "option_set_type": "options_array",
                "options": [
                    {
                        "option_type": "ability_bonus",
                        "ability_score": {
                            "index": "str",
                            "name": "FOR",
                            "url": "/api/ability-scores/str"
                        },
                        "bonus": 1
                    },
                    {
                        "option_type": "ability_bonus",
                        "ability_score": {
                            "index": "dex",
                            "name": "DES",
                            "url": "/api/ability-scores/dex"
                        },
                        "bonus": 1
                    },
                    {
                        "option_type": "ability_bonus",
                        "ability_score": {
                            "index": "con",
                            "name": "CON",
                            "url": "/api/ability-scores/con"
                        },
                        "bonus": 1
                    },
                    {
                        "option_type": "ability_bonus",
                        "ability_score": {
                            "index": "int",
                            "name": "INT",
                            "url": "/api/ability-scores/int"
                        },
                        "bonus": 1
                    },
                    {
                        "option_type": "ability_bonus",
                        "ability_score": {
                            "index": "wis",
                            "name": "SAB",
                            "url": "/api/ability-scores/wis"
                        },
                        "bonus": 1
                    }
                ]
            }
        },
        "alignment": "Meio-elfos compartilham a veia caótica da sua herança élfica. Eles valorizam tanto a sua liberdade quanto sua expressão criativa, não demonstrando qualquer apresso por líderes ou seguidores. Eles se irritam com regras, ressentindo com exigências de outros e, as vezes, se provam incertos, ou pelo menos, imprevisíveis.",
        "age": "Meio-elfos atingem a maturidade ao mesmo tempo que os humanos atingem a idade adulta, por volta dos 20 anos. Eles vivem muito mais que os humanos, no entanto, raramente ultrapassam os 180 anos.",
        "size": "Médio",
        "size_description": "Meio-elfos tem aproximadamente a mesma altura dos humanos, variando entre 1,50 metro e 1,80 metro.",
        "starting_proficiencies": [],
        "starting_proficiency_options": {
            "choose": 2,
            "type": "proficiencies",
            "from": {
                "option_set_type": "options_array",
                "options": [
                    {
                        "option_type": "reference",
                        "item": {
                            "index": "skill-acrobatics",
                            "name": "Habilidade: Acrobacia",
                            "url": "/api/proficiencies/skill-acrobatics"
                        }
                    },
                    {
                        "option_type": "reference",
                        "item": {
                            "index": "skill-animal-handling",
                            "name": "Habilidade: Adestrar Animais",
                            "url": "/api/proficiencies/skill-animal-handling"
                        }
                    },
                    {
                        "option_type": "reference",
                        "item": {
                            "index": "skill-arcana",
                            "name": "Habilidade: Arcanismo",
                            "url": "/api/proficiencies/skill-arcana"
                        }
                    },
                    {
                        "option_type": "reference",
                        "item": {
                            "index": "skill-athletics",
                            "name": "Habilidade: Atletismo",
                            "url": "/api/proficiencies/skill-athletics"
                        }
                    },
                    {
                        "option_type": "reference",
                        "item": {
                            "index": "skill-deception",
                            "name": "Habilidade: Enganação",
                            "url": "/api/proficiencies/skill-deception"
                        }
                    },
                    {
                        "option_type": "reference",
                        "item": {
                            "index": "skill-history",
                            "name": "Habilidade: História",
                            "url": "/api/proficiencies/skill-history"
                        }
                    },
                    {
                        "option_type": "reference",
                        "item": {
                            "index": "skill-insight",
                            "name": "Habilidade: Intuição",
                            "url": "/api/proficiencies/skill-insight"
                        }
                    },
                    {
                        "option_type": "reference",
                        "item": {
                            "index": "skill-intimidation",
                            "name": "Habilidade: Intimidação",
                            "url": "/api/proficiencies/skill-intimidation"
                        }
                    },
                    {
                        "option_type": "reference",
                        "item": {
                            "index": "skill-investigation",
                            "name": "Habilidade: Investigação",
                            "url": "/api/proficiencies/skill-investigation"
                        }
                    },
                    {
                        "option_type": "reference",
                        "item": {
                            "index": "skill-medicine",
                            "name": "Habilidade: Medicina",
                            "url": "/api/proficiencies/skill-medicine"
                        }
                    },
                    {
                        "option_type": "reference",
                        "item": {
                            "index": "skill-nature",
                            "name": "Habilidade: Natureza",
                            "url": "/api/proficiencies/skill-nature"
                        }
                    },
                    {
                        "option_type": "reference",
                        "item": {
                            "index": "skill-perception",
                            "name": "Habilidade: Percepção",
                            "url": "/api/proficiencies/skill-perception"
                        }
                    },
                    {
                        "option_type": "reference",
                        "item": {
                            "index": "skill-performance",
                            "name": "Habilidade: Atuação",
                            "url": "/api/proficiencies/skill-performance"
                        }
                    },
                    {
                        "option_type": "reference",
                        "item": {
                            "index": "skill-persuasion",
                            "name": "Habilidade: Persuasão",
                            "url": "/api/proficiencies/skill-persuasion"
                        }
                    },
                    {
                        "option_type": "reference",
                        "item": {
                            "index": "skill-religion",
                            "name": "Habilidade: Religião",
                            "url": "/api/proficiencies/skill-religion"
                        }
                    },
                    {
                        "option_type": "reference",
                        "item": {
                            "index": "skill-sleight-of-hand",
                            "name": "Habilidade: Prestidigitação",
                            "url": "/api/proficiencies/skill-sleight-of-hand"
                        }
                    },
                    {
                        "option_type": "reference",
                        "item": {
                            "index": "skill-stealth",
                            "name": "Habilidade: Furtividade",
                            "url": "/api/proficiencies/skill-stealth"
                        }
                    },
                    {
                        "option_type": "reference",
                        "item": {
                            "index": "skill-survival",
                            "name": "Habilidade: Sobrevivência",
                            "url": "/api/proficiencies/skill-survival"
                        }
                    }
                ]
            }
        },
        "languages": [
            {
                "index": "common",
                "name": "Comum",
                "url": "/api/languages/common"
            },
            {
                "index": "elvish",
                "name": "Elfico",
                "url": "/api/languages/elvish"
            }
        ],
        "language_options": {
            "choose": 1,
            "type": "languages",
            "from": {
                "option_set_type": "options_array",
                "options": [
                    {
                        "option_type": "reference",
                        "item": {
                            "index": "dwarvish",
                            "name": "Anão",
                            "url": "/api/languages/dwarvish"
                        }
                    },
                    {
                        "option_type": "reference",
                        "item": {
                            "index": "giant",
                            "name": "Gigante",
                            "url": "/api/languages/giant"
                        }
                    },
                    {
                        "option_type": "reference",
                        "item": {
                            "index": "gnomish",
                            "name": "Gnômico",
                            "url": "/api/languages/gnomish"
                        }
                    },
                    {
                        "option_type": "reference",
                        "item": {
                            "index": "goblin",
                            "name": "Goblin",
                            "url": "/api/languages/goblin"
                        }
                    },
                    {
                        "option_type": "reference",
                        "item": {
                            "index": "halfling",
                            "name": "Halfling",
                            "url": "/api/languages/halfling"
                        }
                    },
                    {
                        "option_type": "reference",
                        "item": {
                            "index": "orc",
                            "name": "Orc",
                            "url": "/api/languages/orc"
                        }
                    },
                    {
                        "option_type": "reference",
                        "item": {
                            "index": "abyssal",
                            "name": "Abissal",
                            "url": "/api/languages/abyssal"
                        }
                    },
                    {
                        "option_type": "reference",
                        "item": {
                            "index": "celestial",
                            "name": "Celestial",
                            "url": "/api/languages/celestial"
                        }
                    },
                    {
                        "option_type": "reference",
                        "item": {
                            "index": "draconic",
                            "name": "Draconico",
                            "url": "/api/languages/draconic"
                        }
                    },
                    {
                        "option_type": "reference",
                        "item": {
                            "index": "deep-speech",
                            "name": "Dialeto Subterrâneo",
                            "url": "/api/languages/deep-speech"
                        }
                    },
                    {
                        "option_type": "reference",
                        "item": {
                            "index": "infernal",
                            "name": "Infernal",
                            "url": "/api/languages/infernal"
                        }
                    },
                    {
                        "option_type": "reference",
                        "item": {
                            "index": "primordial",
                            "name": "Primordial",
                            "url": "/api/languages/primordial"
                        }
                    },
                    {
                        "option_type": "reference",
                        "item": {
                            "index": "sylvan",
                            "name": "Silvestre",
                            "url": "/api/languages/sylvan"
                        }
                    },
                    {
                        "option_type": "reference",
                        "item": {
                            "index": "undercommon",
                            "name": "Subcomum",
                            "url": "/api/languages/undercommon"
                        }
                    }
                ]
            }
        },
        "language_desc": "Você sabe falar, ler e escrever Comum, Élfico e um idioma adicional, à sua escolha.",
        "traits": [
            {
                "index": "darkvision",
                "name": "Visão no Escuro",
                "url": "/api/traits/darkvision"
            },
            {
                "index": "fey-ancestry",
                "name": "Ancestral Feérico",
                "url": "/api/traits/fey-ancestry"
            },
            {
                "index": "skill-versatility",
                "name": "Versatilidade em Perícia",
                "url": "/api/traits/skill-versatility"
            }
        ],
        "subraces": [],
        "url": "/api/races/half-elf"
    },
    {
        "index": "half-orc",
        "name": "Meio-Orc:",
        "speed": 9,
        "ability_bonuses": [
            {
                "ability_score": {
                    "index": "str",
                    "name": "FOR",
                    "url": "/api/ability-scores/str"
                },
                "bonus": 2
            },
            {
                "ability_score": {
                    "index": "con",
                    "name": "CON",
                    "url": "/api/ability-scores/con"
                },
                "bonus": 1
            }
        ],
        "alignment": "Meio-orcs tem uma tendência inata ao caos devido aos seus parentes orcs e não são fortemente inclinados ao bem. Meio-orcs que cresceram entre orcs e desejam viver e estão dispostos a passar sua vida entre eles, tendem a ser malignos.",
        "age": "Os meio-orcs amadurecem um pouco antes dos humanos, atingindo a idade adulta aos 14 anos. Eles envelhecem notavelmente mais rápido e, raramente, vivem mais de 75 anos.",
        "size": "Médio",
        "size_description": "Meio-orcs são de certa forma maiores e mais largos que os humanos, medindo entre 1,80 metro e 2,10 metros.",
        "starting_proficiencies": [
            {
                "index": "skill-intimidation",
                "name": "Habilidade: Intimidação",
                "url": "/api/proficiencies/skill-intimidation"
            }
        ],
        "languages": [
            {
                "index": "common",
                "name": "Comum",
                "url": "/api/languages/common"
            },
            {
                "index": "orc",
                "name": "Orc",
                "url": "/api/languages/orc"
            }
        ],
        "language_desc": "Você sabe falar, ler e escrever Comum, Orc. O Orc é um idioma ríspido, possuindo uma linguagem de consoantes duras. Ele não possui alfabeto próprio, mas usa o alfabeto Anão.",
        "traits": [
            {
                "index": "darkvision",
                "name": "Visão no Escuro",
                "url": "/api/traits/darkvision"
            },
            {
                "index": "savage-attacks",
                "name": "Ataques Selvagens",
                "url": "/api/traits/savage-attacks"
            },
            {
                "index": "relentless-endurance",
                "name": "Resistência Implacável",
                "url": "/api/traits/relentless-endurance"
            },
            {
                "index": "menacing",
                "name": "Ameaçador",
                "url": "/api/traits/menacing"
            }
        ],
        "subraces": [],
        "url": "/api/races/half-orc"
    },
    {
        "index": "halfling",
        "name": "Halflings",
        "speed": 7.5,
        "ability_bonuses": [
            {
                "ability_score": {
                    "index": "dex",
                    "name": "DES",
                    "url": "/api/ability-scores/dex"
                },
                "bonus": 2
            }
        ],
        "age": "Um halfling atinge a idade adulta aos 20 anos e pode chegar a 150 anos.",
        "alignment": "A maioria dos halflings é leal e boa. Via de regra, eles possuem um bom coração e são amáveis, odeiam ver o sofrimento dos outros e não toleram a opressão. Eles também são muito ordeiros e tradicionais, fortemente apegados à sua comunidade e ao conforto de suas antigas tradições.",
        "size": "Pequeno",
        "size_description": " Halflings medem cerca de 0,90 metro de altura e pesam aproximadamente 20 kg.",
        "starting_proficiencies": [],
        "languages": [
            {
                "index": "common",
                "name": "Comum",
                "url": "/api/languages/common"
            },
            {
                "index": "halfling",
                "name": "Halfling",
                "url": "/api/languages/halfling"
            }
        ],
        "language_desc": "Você pode falar, ler e escrever Comum e Halfling. A linguagem Halfling não é secreta, mas os halflings são relutantes em compartilhá-la com os outros. Eles escrevem muito pouco, por isso eles não possuem uma literatura rica. No entanto, sua tradição oral é muito forte. Quase todos os halflings falam o idioma Comum para conversar com as pessoas das terras que habitam, ou através das quais eles estejam viajando.",
        "traits": [
            {
                "index": "brave",
                "name": "Bravura",
                "url": "/api/traits/brave"
            },
            {
                "index": "halfling-nimbleness",
                "name": "Agilidade Halfling",
                "url": "/api/traits/halfling-nimbleness"
            },
            {
                "index": "lucky",
                "name": "Sortudo",
                "url": "/api/traits/lucky"
            }
        ],
        "subraces": [
            {
                "index": "lightfoot-halfling",
                "name": "Halfling Pés Leves",
                "url": "/api/subraces/lightfoot-halfling"
            }
        ],
        "url": "/api/races/halfling"
    },
    {
        "index": "human",
        "name": "Humano",
        "speed": 9,
        "ability_bonuses": [
            {
                "ability_score": {
                    "index": "str",
                    "name": "FOR",
                    "url": "/api/ability-scores/str"
                },
                "bonus": 1
            },
            {
                "ability_score": {
                    "index": "dex",
                    "name": "DES",
                    "url": "/api/ability-scores/dex"
                },
                "bonus": 1
            },
            {
                "ability_score": {
                    "index": "con",
                    "name": "CON",
                    "url": "/api/ability-scores/con"
                },
                "bonus": 1
            },
            {
                "ability_score": {
                    "index": "int",
                    "name": "INT",
                    "url": "/api/ability-scores/int"
                },
                "bonus": 1
            },
            {
                "ability_score": {
                    "index": "wis",
                    "name": "SAB",
                    "url": "/api/ability-scores/wis"
                },
                "bonus": 1
            },
            {
                "ability_score": {
                    "index": "cha",
                    "name": "CAR",
                    "url": "/api/ability-scores/cha"
                },
                "bonus": 1
            }
        ],
        "age": "Os humanos chegam à idade adulta no final da adolescência e vivem menos de um século.",
        "alignment": "Os humanos não possuem inclinação a nenhuma tendência em especial. Os melhores e os piores são encontrados entre eles. ",
        "size": "Médio",
        "size_description": " Os humanos variam muito em altura e peso, podem ter quase 1,50 metro ou mais de 1,80 metro. Independentemente da sua posição entre esses valores.",
        "starting_proficiencies": [],
        "languages": [
            {
                "index": "common",
                "name": "Comum",
                "url": "/api/languages/common"
            }
        ],
        "language_options": {
            "choose": 1,
            "type": "languages",
            "from": {
                "option_set_type": "options_array",
                "options": [
                    {
                        "option_type": "reference",
                        "item": {
                            "index": "dwarvish",
                            "name": "Anão",
                            "url": "/api/languages/dwarvish"
                        }
                    },
                    {
                        "option_type": "reference",
                        "item": {
                            "index": "elvish",
                            "name": "Elfico",
                            "url": "/api/languages/elvish"
                        }
                    },
                    {
                        "option_type": "reference",
                        "item": {
                            "index": "giant",
                            "name": "Gigante",
                            "url": "/api/languages/giant"
                        }
                    },
                    {
                        "option_type": "reference",
                        "item": {
                            "index": "gnomish",
                            "name": "Gnômico",
                            "url": "/api/languages/gnomish"
                        }
                    },
                    {
                        "option_type": "reference",
                        "item": {
                            "index": "goblin",
                            "name": "Goblin",
                            "url": "/api/languages/goblin"
                        }
                    },
                    {
                        "option_type": "reference",
                        "item": {
                            "index": "halfling",
                            "name": "Halfling",
                            "url": "/api/languages/halfling"
                        }
                    },
                    {
                        "option_type": "reference",
                        "item": {
                            "index": "orc",
                            "name": "Orc",
                            "url": "/api/languages/orc"
                        }
                    },
                    {
                        "option_type": "reference",
                        "item": {
                            "index": "abyssal",
                            "name": "Abissal",
                            "url": "/api/languages/abyssal"
                        }
                    },
                    {
                        "option_type": "reference",
                        "item": {
                            "index": "celestial",
                            "name": "Celestial",
                            "url": "/api/languages/celestial"
                        }
                    },
                    {
                        "option_type": "reference",
                        "item": {
                            "index": "draconic",
                            "name": "Draconico",
                            "url": "/api/languages/draconic"
                        }
                    },
                    {
                        "option_type": "reference",
                        "item": {
                            "index": "deep-speech",
                            "name": "Dialeto Subterrâneo",
                            "url": "/api/languages/deep-speech"
                        }
                    },
                    {
                        "option_type": "reference",
                        "item": {
                            "index": "infernal",
                            "name": "Infernal",
                            "url": "/api/languages/infernal"
                        }
                    },
                    {
                        "option_type": "reference",
                        "item": {
                            "index": "primordial",
                            "name": "Primordial",
                            "url": "/api/languages/primordial"
                        }
                    },
                    {
                        "option_type": "reference",
                        "item": {
                            "index": "sylvan",
                            "name": "Silvestre",
                            "url": "/api/languages/sylvan"
                        }
                    },
                    {
                        "option_type": "reference",
                        "item": {
                            "index": "undercommon",
                            "name": "Subcomum",
                            "url": "/api/languages/undercommon"
                        }
                    }
                ]
            }
        },
        "language_desc": "Você pode falar, ler e escrever Comum e outro idioma adicional, à sua escolha. Os humanos normalmente aprendem os idiomas dos povos que convivem, incluindo dialetos obscuros. Eles gostam de rechear seu discurso com palavras emprestadas de outras línguas: xingamentos orcs, expressões musicais élficas, frases militares anãs e outros.",
        "traits": [],
        "subraces": [],
        "url": "/api/races/human"
    },
    {
        "index": "tiefling",
        "name": "Tiefling",
        "speed": 9,
        "ability_bonuses": [
            {
                "ability_score": {
                    "index": "int",
                    "name": "INT",
                    "url": "/api/ability-scores/int"
                },
                "bonus": 1
            },
            {
                "ability_score": {
                    "index": "cha",
                    "name": "CAR",
                    "url": "/api/ability-scores/cha"
                },
                "bonus": 2
            }
        ],
        "alignment": "Tieflings não possuem uma tendência inata ao mal, mas muitos acabam por abraçá-lo. Maligno ou não, uma natureza independente inclina a maioria dos tieflings ao alinhamento caótico.",
        "age": "Os tieflings amadurecem ao mesmo tempo que os humanos, mas vivem alguns anos a mais.",
        "size": "Médio",
        "size_description": "Os tieflings possuem o mesmo tamanho e compleição dos humanos.",
        "starting_proficiencies": [],
        "languages": [
            {
                "index": "common",
                "name": "Comum",
                "url": "/api/languages/common"
            },
            {
                "index": "infernal",
                "name": "Infernal",
                "url": "/api/languages/infernal"
            }
        ],
        "language_desc": "Você pode falar, ler e escrever Comum e Infernal.",
        "traits": [
            {
                "index": "darkvision",
                "name": "Visão no Escuro",
                "url": "/api/traits/darkvision"
            },
            {
                "index": "hellish-resistance",
                "name": "Resistência Infernal",
                "url": "/api/traits/hellish-resistance"
            },
            {
                "index": "infernal-legacy",
                "name": "Legado Infernal",
                "url": "/api/traits/infernal-legacy"
            }
        ],
        "subraces": [],
        "url": "/api/races/tiefling"
    }
]
